events_bus/__init__.py
events_bus/aws/event_bridge_publisher.py
events_bus/aws/mangum.py
events_bus/aws/sqs_dispatcher.py
events_bus/config.py
events_bus/core/__init__.py
events_bus/core/contracts/base_event.py
events_bus/core/contracts/deduplication.py
events_bus/core/contracts/failover.py
events_bus/core/contracts/handler.py
events_bus/core/infrastructure/event_bus_publisher.py
events_bus/core/infrastructure/event_deserializer.py
events_bus/core/infrastructure/event_serializer.py
events_bus/core/infrastructure/local_failover.py
events_bus/core/infrastructure/redis_deduplication.py
events_bus/core/infrastructure/redis_failover.py
events_bus/core/runtime/event_register.py
events_bus/exceptions.py
events_bus/py.typed
events_bus/typing.py
package_events_bus-0.1.39.dist-info/LICENSE
package_events_bus-0.1.39.dist-info/METADATA
package_events_bus-0.1.39.dist-info/WHEEL
package_events_bus-0.1.39.dist-info/RECORD
