Metadata-Version: 2.3
Name: package-events-bus
Version: 0.1.39
Summary: Una librería para construir microservicios desacoplados en Python usando AWS EventBridge y SQS, donde cada caso de uso maneja su propia cola y se despacha automáticamente mediante handlers tipados.
License: MIT
Author: Jose Luis Rosales Meza
Author-email: jose.rosales@finkargo.com
Requires-Python: >=3.10,<4.0
Classifier: License :: OSI Approved :: MIT License
Classifier: Programming Language :: Python :: 3
Classifier: Programming Language :: Python :: 3.10
Classifier: Programming Language :: Python :: 3.11
Classifier: Programming Language :: Python :: 3.12
Classifier: Programming Language :: Python :: 3.13
Requires-Dist: boto3 (>=1.38.13,<2.0.0)
Requires-Dist: mangum (>=0.19.0,<0.20.0)
Requires-Dist: pytest (>=8.4.0,<9.0.0)
Requires-Dist: python-dotenv (>=1.1.0,<2.0.0)
Requires-Dist: redis (>=5.0,<6.0)
